PyOphidia/__init__.py
PyOphidia/client.py
PyOphidia/cube.py
PyOphidia/ophsubmit.py
PyOphidia-1.11.0.dist-info/AUTHORS.rst
PyOphidia-1.11.0.dist-info/LICENSE
PyOphidia-1.11.0.dist-info/METADATA
PyOphidia-1.11.0.dist-info/NOTICE.rst
PyOphidia-1.11.0.dist-info/WHEEL
PyOphidia-1.11.0.dist-info/top_level.txt
PyOphidia-1.11.0.dist-info/RECORD
