Metadata-Version: 2.1
Name: PyOphidia
Version: 1.11.0
Summary: Python bindings for the Ophidia Data Analytics Platform
Home-page: http://ophidia.cmcc.it
Author: Ophidia Developers
Author-email: ophidia-info@cmcc.it
License: GPLv3+
Platform: UNKNOWN
Classifier: Development Status :: 5 - Production/Stable
Classifier: Intended Audience :: Developers
Classifier: Natural Language :: English
Classifier: License :: OSI Approved :: GNU General Public License v3 or later (GPLv3+)
Classifier: Operating System :: OS Independent
Classifier: Programming Language :: Python
Classifier: Programming Language :: Python :: 2
Classifier: Programming Language :: Python :: 2.7
Classifier: Programming Language :: Python :: 3
Classifier: Programming Language :: Python :: 3.7
Classifier: Programming Language :: Python :: 3.8
Classifier: Programming Language :: Python :: 3.9
Classifier: Programming Language :: Python :: 3.10
Classifier: Programming Language :: Python :: 3.11
Classifier: Topic :: Software Development :: Libraries :: Python Modules
Classifier: Topic :: Scientific/Engineering
Provides-Extra: convert
Requires-Dist: numpy (>=1.19) ; extra == 'convert'
Requires-Dist: pandas (>=1.2) ; extra == 'convert'
Requires-Dist: xarray ; extra == 'convert'
